lightning_colossalai/__about__.py
lightning_colossalai/__init__.py
lightning_colossalai/precision.py
lightning_colossalai/strategy.py
lightning_colossalai-0.1.0.dist-info/LICENSE
lightning_colossalai-0.1.0.dist-info/METADATA
lightning_colossalai-0.1.0.dist-info/WHEEL
lightning_colossalai-0.1.0.dist-info/top_level.txt
lightning_colossalai-0.1.0.dist-info/RECORD
