Metadata-Version: 2.1
Name: lightning-colossalai
Version: 0.1.0
Summary: Efficient Large-Scale Distributed Training with Colossal-AI and Lightning AI.
Home-page: https://github.com/Lightning-AI/lightning-colossalai
Download-URL: https://github.com/Lightning-AI/lightning-colossalai
Author: Lightning-AI et al.
Author-email: name@lightning.ai
License: Apache-2.0
Project-URL: Bug Tracker, https://github.com/Lightning-AI/lightning-colossalai/issues
Project-URL: Documentation, https://lightning-ai.github.io/lightning-ColossalAI/
Project-URL: Source Code, https://github.com/Lightning-AI/lightning-colossalai
Keywords: deep learning,pytorch,AI
Classifier: Environment :: Console
Classifier: Natural Language :: English
Classifier: Development Status :: 4 - Beta
Classifier: Intended Audience :: Developers
Classifier: Topic :: Scientific/Engineering :: Artificial Intelligence
Classifier: Topic :: Scientific/Engineering :: Information Analysis
Classifier: License :: OSI Approved :: Apache Software License
Classifier: Operating System :: OS Independent
Classifier: Programming Language :: Python :: 3
Classifier: Programming Language :: Python :: 3.8
Classifier: Programming Language :: Python :: 3.9
Classifier: Programming Language :: Python :: 3.10
Classifier: Programming Language :: Python :: 3.11
Requires-Python: >=3.8
License-File: LICENSE
Requires-Dist: lightning (>=2.0.0)
Requires-Dist: colossalai (>=0.2.0)
Requires-Dist: torch (<2.0.0)
